{"fine_grained_deps": {}, "tree": {".class": "MypyFile", "_fullname": "xml.etree", "_name": null, "is_stub": true, "names": {".class": "SymbolTable", "__doc__": {".class": "SymbolTableNode", "kind": "Gdef", "node": {".class": "Var", "flags": [], "fullname": "xml.etree.__doc__", "name": "__doc__", "type": "builtins.str"}}, "__file__": {".class": "SymbolTableNode", "kind": "Gdef", "node": {".class": "Var", "flags": [], "fullname": "xml.etree.__file__", "name": "__file__", "type": "builtins.str"}}, "__name__": {".class": "SymbolTableNode", "kind": "Gdef", "node": {".class": "Var", "flags": [], "fullname": "xml.etree.__name__", "name": "__name__", "type": "builtins.str"}}, "__package__": {".class": "SymbolTableNode", "kind": "Gdef", "node": {".class": "Var", "flags": [], "fullname": "xml.etree.__package__", "name": "__package__", "type": "builtins.str"}}}, "path": "C:\\Users\\marko\\AppData\\Roaming\\Python\\lib\\mypy\\typeshed\\stdlib\\2and3\\xml\\etree\\__init__.pyi"}}
