{"id": "http", "path": "C:\\Users\\marko\\AppData\\Roaming\\Python\\lib\\mypy\\typeshed\\stdlib\\3\\http\\__init__.pyi", "mtime": 1521805414, "size": 3103, "hash": "1a531361917ff0c473d2bf656cbedde9", "data_mtime": 1537353160, "dependencies": ["sys", "enum", "builtins"], "suppressed": [], "child_modules": ["http.cookiejar", "http.client"], "options": {"disallow_any_expr": false, "disallow_untyped_decorators": false, "follow_imports": "silent", "disallow_untyped_defs": false, "no_implicit_optional": false, "cache_fine_grained": false, "platform": "win32", "disallow_any_generics": false, "warn_no_return": true, "disallow_any_explicit": false, "warn_return_any": false, "disallow_untyped_calls": false, "check_untyped_defs": false, "warn_unused_ignores": false, "strict_optional": false, "disallow_any_decorated": false, "disallow_any_unimported": false, "disallow_subclassing_any": false, "strict_optional_whitelist": null, "ignore_errors": false, "strict_boolean": false, "ignore_missing_imports": true, "show_none_errors": true, "quick_and_dirty": false}, "dep_prios": [10, 5, 5], "dep_lines": [1, 3, 1], "interface_hash": "49826335dd5e9b022157a0b826fbd4d9", "version_id": "0.570", "ignore_all": false}
