{"id": "ssl", "path": "C:\\Users\\marko\\AppData\\Roaming\\Python\\lib\\mypy\\typeshed\\stdlib\\3\\ssl.pyi", "mtime": 1521805413, "size": 12761, "hash": "41c8b74ea1be363f3ab704068eecac0e", "data_mtime": 1537617378, "dependencies": ["typing", "socket", "sys", "builtins"], "suppressed": [], "child_modules": [], "options": {"disallow_any_generics": false, "disallow_any_expr": false, "no_implicit_optional": false, "disallow_subclassing_any": false, "disallow_any_explicit": false, "disallow_untyped_decorators": false, "check_untyped_defs": false, "ignore_errors": false, "follow_imports": "silent", "warn_return_any": false, "warn_no_return": true, "warn_unused_ignores": false, "disallow_untyped_calls": false, "disallow_any_unimported": false, "disallow_untyped_defs": false, "show_none_errors": true, "ignore_missing_imports": true, "strict_optional_whitelist": null, "strict_optional": false, "quick_and_dirty": false, "strict_boolean": false, "disallow_any_decorated": false, "platform": "win32", "cache_fine_grained": false}, "dep_prios": [5, 10, 10, 5], "dep_lines": [3, 6, 7, 1], "interface_hash": "53a6e38fdf9739fbe97eb6f6c9734695", "version_id": "0.570", "ignore_all": false}
